diskloaf/loaf.py
diskloaf-0.3.0.dist-info/METADATA
diskloaf-0.3.0.dist-info/WHEEL
diskloaf-0.3.0.dist-info/entry_points.txt
diskloaf-0.3.0.dist-info/top_level.txt
diskloaf-0.3.0.dist-info/RECORD
